README.md
setup.py
flask_man/__init__.py
flask_man/__main__.py
flask_man/d.py
flask_man.egg-info/PKG-INFO
flask_man.egg-info/SOURCES.txt
flask_man.egg-info/dependency_links.txt
flask_man.egg-info/entry_points.txt
flask_man.egg-info/requires.txt
flask_man.egg-info/top_level.txt