Metadata-Version: 2.1
Name: flask-man
Version: 1.2.0
Summary: Flask module to auto setup and manage the project and its configurations (app code, templates, databases...)
Home-page: https://github.com/AlaBouali/flask_man
Author: AlaBouali
Author-email: trap.leader.123@gmail.com
License: MIT License
Platform: UNKNOWN
Classifier: Programming Language :: Python
Classifier: License :: OSI Approved :: MIT License 
Requires-Python: >=2.7
